gitthread/__init__.py
gitthread/__main__.py
gitthread/app.py
gitthread/ingestor.py
gitthread/parser.py
gitthread/web.py
gitthread/server/main.py
gitthread-0.1.1.dist-info/licenses/LICENSE
gitthread-0.1.1.dist-info/METADATA
gitthread-0.1.1.dist-info/WHEEL
gitthread-0.1.1.dist-info/entry_points.txt
gitthread-0.1.1.dist-info/top_level.txt
gitthread-0.1.1.dist-info/RECORD
