Metadata-Version: 2.4
Name: gitthread
Version: 0.1.1
Summary: Ingest GitHub Issues and Pull Requests into LLM-friendly text dumps
Requires-Python: >=3.8
License-File: LICENSE
Requires-Dist: click>=8.0.0
Requires-Dist: PyGithub>=2.0.0
Requires-Dist: gitingest>=0.3.1
Requires-Dist: httpx
Requires-Dist: loguru>=0.7.0
Requires-Dist: pydantic
Requires-Dist: python-dotenv
Requires-Dist: tiktoken>=0.7.0
Requires-Dist: streamlit
Provides-Extra: dev
Requires-Dist: pytest; extra == "dev"
Requires-Dist: pytest-asyncio; extra == "dev"
Provides-Extra: server
Requires-Dist: fastapi[standard]>=0.109.1; extra == "server"
Requires-Dist: uvicorn>=0.11.7; extra == "server"
Dynamic: license-file
